Metadata-Version: 2.1
Name: odoo-addon-l10n_es_aeat
Version: 18.0.1.3.6.3
Requires-Python: >=3.10
Requires-Dist: odoo-addon-account_tax_balance==18.0.*
Requires-Dist: odoo==18.0.*
Requires-Dist: unidecode
Summary: Modulo base para declaraciones de la AEAT
Home-page: https://github.com/OCA/l10n-spain
License: AGPL-3
Author: Pexego, Acysos S.L., AvanzOSC, Tecnativa, Odoo Community Association (OCA)
Author-email: support@odoo-community.org
Classifier: Programming Language :: Python
Classifier: Framework :: Odoo
Classifier: Framework :: Odoo :: 18.0
Classifier: License :: OSI Approved :: GNU Affero General Public License v3
Classifier: Development Status :: 6 - Mature
